README.txt
setup.py
Products/__init__.py
Products.FinanceFields.egg-info/PKG-INFO
Products.FinanceFields.egg-info/SOURCES.txt
Products.FinanceFields.egg-info/dependency_links.txt
Products.FinanceFields.egg-info/entry_points.txt
Products.FinanceFields.egg-info/namespace_packages.txt
Products.FinanceFields.egg-info/not-zip-safe
Products.FinanceFields.egg-info/requires.txt
Products.FinanceFields.egg-info/top_level.txt
Products/FinanceFields/Currency.py
Products/FinanceFields/CurrencyField.py
Products/FinanceFields/FixedPointField.py
Products/FinanceFields/Money.py
Products/FinanceFields/MoneyField.py
Products/FinanceFields/MoneyWidget.py
Products/FinanceFields/README.txt
Products/FinanceFields/__init__.py
Products/FinanceFields/config.py
Products/FinanceFields/fixedpoint.py
Products/FinanceFields/tests.py
Products/FinanceFields/version.txt
Products/FinanceFields/Extensions/Install.py
Products/FinanceFields/Extensions/commit_subtransaction.py
Products/FinanceFields/profiles/default/propertiestool.xml
Products/FinanceFields/skins/financefields/money.pt
docs/HISTORY.txt