Metadata-Version: 1.0
Name: Products.FinanceFields
Version: 1.0
Summary: Archetypes field for the proper handling of monetary and fixed point values
Home-page: UNKNOWN
Author: RC Compaan
Author-email: roche at upfrontsystems dot co dot za
License: GPL
Keywords: financial money fixed-point
Platform: UNKNOWN
Classifier: Programming Language :: Python
